rstar_python-0.0.2.dist-info/METADATA
rstar_python-0.0.2.dist-info/WHEEL
rstar_python-0.0.2.dist-info/licenses/LICENSE
rstar_python/__init__.py
rstar_python/rstar_python.cp39-win_amd64.pyd
rstar_python-0.0.2.dist-info/RECORD
