Metadata-Version: 2.4
Name: rstar-python
Version: 0.0.2
Classifier: Development Status :: 3 - Alpha
Classifier: Intended Audience :: Developers
Classifier: License :: OSI Approved :: MIT License
Classifier: Programming Language :: Python :: 3
Classifier: Programming Language :: Python :: 3.10
Classifier: Programming Language :: Python :: 3.11
Classifier: Programming Language :: Python :: 3.12
Classifier: Programming Language :: Rust
Classifier: Operating System :: POSIX :: Linux
Classifier: Operating System :: MacOS
Classifier: Operating System :: Microsoft :: Windows
Requires-Dist: numpy>=1.21.6
License-File: LICENSE
Summary: Python bindings for the rstar R*-tree spatial index
Home-Page: https://github.com/kephale/rstar-python
Author-email: Kyle Harrington <kyle@kyleharrington.com>
License: MIT
Requires-Python: >=3.10
Project-URL: Homepage, https://github.com/kephale/rstar-python
Project-URL: Repository, https://github.com/kephale/rstar-python
Project-URL: Issues, https://github.com/kephale/rstar-python/issues
